cabot_alert_hipchat/__init__.py
cabot_alert_hipchat/models.py
cabot_alert_hipchat/migrations/0001_initial.py
cabot_alert_hipchat/migrations/__init__.py
cabot_alert_hipchat/tests/__init__.py
cabot_alert_hipchat/tests/test_hipchat.py
cabot_alert_hipchat-2.0.3.dist-info/DESCRIPTION.rst
cabot_alert_hipchat-2.0.3.dist-info/METADATA
cabot_alert_hipchat-2.0.3.dist-info/RECORD
cabot_alert_hipchat-2.0.3.dist-info/WHEEL
cabot_alert_hipchat-2.0.3.dist-info/metadata.json
cabot_alert_hipchat-2.0.3.dist-info/top_level.txt
