Metadata-Version: 2.0
Name: cabot-alert-hipchat
Version: 2.0.3
Summary: A Hipchat alert plugin for Cabot by Arachnys
Home-page: http://cabotapp.com
Author: Arachnys
Author-email: info@arachnys.com
License: UNKNOWN
Download-URL: https://github.com/cabotapp/cabot-alert-hipchat/archive/2.0.3.zip
Platform: UNKNOWN
